hl_gauss_pytorch/__init__.py
hl_gauss_pytorch/binary_hl_gauss.py
hl_gauss_pytorch/hl_gauss.py
hl_gauss_pytorch-0.1.24.dist-info/METADATA
hl_gauss_pytorch-0.1.24.dist-info/WHEEL
hl_gauss_pytorch-0.1.24.dist-info/licenses/LICENSE
hl_gauss_pytorch-0.1.24.dist-info/RECORD
