Metadata-Version: 2.4
Name: hl-gauss-pytorch
Version: 0.1.24
Summary: HL Gauss - Pytorch
Project-URL: Homepage, https://pypi.org/project/hl-gauss-pytorch/
Project-URL: Repository, https://github.com/lucidrains/hl-gauss-pytorch
Author-email: Phil Wang <lucidrains@gmail.com>
License: MIT License
License-File: LICENSE
Keywords: artificial intelligence,deep learning,regression as classification
Classifier: Development Status :: 4 - Beta
Classifier: Intended Audience :: Developers
Classifier: License :: OSI Approved :: MIT License
Classifier: Programming Language :: Python :: 3.9
Classifier: Topic :: Scientific/Engineering :: Artificial Intelligence
Requires-Python: >=3.9
Requires-Dist: einops>=0.8.0
Requires-Dist: einx>=0.3.0
Requires-Dist: torch>=2.3
Provides-Extra: examples
Requires-Dist: tqdm; extra == 'examples'
Provides-Extra: test
Requires-Dist: pytest; extra == 'test'
